decision_tree/__init__.py
decision_tree/classifier.py
decision_tree/draw_tree.py
decision_tree/main.py
decision_tree/metrics.py
decision_tree/node.py
decision_tree/plots.py
vsamoilov_eng_prac-1.0.1.dist-info/METADATA
vsamoilov_eng_prac-1.0.1.dist-info/WHEEL
vsamoilov_eng_prac-1.0.1.dist-info/entry_points.txt
vsamoilov_eng_prac-1.0.1.dist-info/top_level.txt
vsamoilov_eng_prac-1.0.1.dist-info/RECORD
