Metadata-Version: 2.1
Name: vsamoilov-eng-prac
Version: 1.0.1
Summary: Homework for eng prac
Author-email: Vitya Samoilov <victor.samoilov.1234@gmail.com>
Project-URL: Homepage, https://github.com/Atos1337/EngineeringPracticesML
Requires-Python: >=3.9
Requires-Dist: matplotlib (>=3.4.3)
Requires-Dist: numpy (>=1.21.3)
Requires-Dist: scikit-learn (>=1.1.3)
Provides-Extra: dev
Requires-Dist: pytest ; extra == 'dev'
Requires-Dist: pip-tools ; extra == 'dev'
Requires-Dist: jupyter ; extra == 'dev'
